fastqsplitter-1.2.0.dist-info/entry_points.txt
fastqsplitter-1.2.0.dist-info/top_level.txt
fastqsplitter-1.2.0.dist-info/WHEEL
fastqsplitter-1.2.0.dist-info/RECORD
fastqsplitter-1.2.0.dist-info/METADATA
fastqsplitter-1.2.0.dist-info/LICENSE.txt
fastqsplitter/split_cy.pyx
fastqsplitter/split_py.py
fastqsplitter/__init__.py
fastqsplitter/split_cy.cpython-36m-x86_64-linux-gnu.so
