Metadata-Version: 2.1
Name: fastqsplitter
Version: 1.2.0
Summary: Splits FASTQ files evenly.
Home-page: https://github.com/LUMC/fastqsplitter
Author: Leiden University Medical Center
Author-email: sasc@lumc.nl
License: MIT
Keywords: fastq split
Platform: UNKNOWN
Classifier: Programming Language :: Python :: 3 :: Only
Classifier: Programming Language :: Python :: 3
Classifier: Programming Language :: Python :: 3.5
Classifier: Programming Language :: Python :: 3.6
Classifier: Programming Language :: Python :: 3.7
Classifier: Programming Language :: Cython
Classifier: License :: OSI Approved :: MIT License
Classifier: Topic :: Scientific/Engineering :: Bio-Informatics
Requires-Python: >=3.5
Requires-Dist: xopen (>=0.8.1)
